macross_serial/__init__.py
macross_serial/async_serial.py
macross_serial/macross_serial.py
macross_serial/multiprocessing.py
macross_serial/tsv_parser.py
macross_serial/util.py
macross_serial/validator.py
macross_serial-1.1.0.dist-info/entry_points.txt
macross_serial-1.1.0.dist-info/WHEEL
macross_serial-1.1.0.dist-info/METADATA
macross_serial-1.1.0.dist-info/RECORD
