Metadata-Version: 2.1
Name: macross-serial
Version: 1.1.0
Summary: 
Home-page: https://github.com/rondou/macross-serial
Author: Rondou Chen
Author-email: 40and44sis@gmail.com
Requires-Python: >=3.8.1,<4.0.0
Classifier: Programming Language :: Python :: 3
Requires-Dist: aioserial
Requires-Dist: ipcq (>=1.1.1,<2.0.0)
Requires-Dist: plumbum
